capturer/__init__.py
capturer/tests.py
capturer-3.0.dist-info/LICENSE.txt
capturer-3.0.dist-info/METADATA
capturer-3.0.dist-info/WHEEL
capturer-3.0.dist-info/top_level.txt
capturer-3.0.dist-info/RECORD
